setup.py
skywise_model.egg-info/PKG-INFO
skywise_model.egg-info/SOURCES.txt
skywise_model.egg-info/dependency_links.txt
skywise_model.egg-info/not-zip-safe
skywise_model.egg-info/requires.txt
skywise_model.egg-info/top_level.txt
skywisemodel/__init__.py
skywisemodel/_subscription.py
skywisemodel/_timeseries.py
skywisemodel/_validation.py
skywisemodel/_variable.py
skywisemodel/event.py
skywisemodel/exc.py
skywisemodel/forecast.py
skywisemodel/model.py