Metadata-Version: 1.1
Name: skywise-model
Version: 0.0.16
Summary: SkyWise Model API Python Client Library
Home-page: https://github.com/wdtinc/skywise-model-py
Author: Weather Decision Technologies
Author-email: jstewart@wdtinc.com
License: UNKNOWN
Platform: UNKNOWN
Classifier: Development Status :: 3 - Alpha
Classifier: Intended Audience :: Developers
Classifier: Natural Language :: English
Classifier: Programming Language :: Python
Classifier: Programming Language :: Python :: 2.7
